[{"id": 0, "date": "2015-01-04", "uid": "dffad027-3589-497b-b240-19e5f1d72f20", "lemma": "['other', 'beach', 'bar', 'snafu', 'experience', 'poor', 'service', 'reception', 'hospitality']", "sentence": "Other than the beach bar snafu I did not experience any poor service by reception or hospitality", "cpt": "0", "category": "atmosphere"}, {"id": 1, "date": "2015-03-11", "uid": "23b5d89a-c2bf-423f-b8dd-46718387b7c3", "lemma": "['go', 'refurbish', 'main', 'hotel', 'close', 'week', 'save', 'guest', 'inconvenience', 'terrible', 'experience']", "sentence": "if your going to refurbish the main part of the hotel why not close for six weeks and save guests the inconvenience of a terrible experience", "cpt": "0", "category": "atmosphere"}, {"id": 2, "date": "2015-03-25", "uid": "1a480dd3-9079-4f41-a088-5cc1dc77a254", "lemma": "['blue', 'paint', 'exterior', 'bring', 'memory', 'old', 'las', 'vegas', '60']", "sentence": "The blue paint on the exterior brings memories of OLD Las Vegas back in the 60s", "cpt": "0", "category": "atmosphere"}, {"id": 3, "date": "2015-08-16", "uid": "8de4e556-6a37-4b4c-b1bc-bb64e8e6f329", "lemma": "['bad', 'experience', 'inclusive']", "sentence": "One bad experience is enough for 400 non inclusive", "cpt": "0", "category": "atmosphere"}, {"id": 4, "date": "2016-06-03", "uid": "de251a14-3d6b-4906-ba7c-2436ed7f03c9", "lemma": "['building', 'little', 'old', 'casino', 'little', 'dingy', 'good', 'quality', 'experience']", "sentence": "the building is a little old casino is a little dingy but it is a good quality experience", "cpt": "0", "category": "atmosphere"}, {"id": 5, "date": "2016-12-31", "uid": "b1cb9fe9-9a35-46f0-b2e2-2870b8754d05", "lemma": "['recommend', 'stay', 'hilton', 'base', 'experience']", "sentence": "I would not recommend anyone to stay in a Hilton based on what we experienced", "cpt": "0", "category": "atmosphere"}, {"id": 6, "date": "2018-03-19", "uid": "e41edf4c-7be0-47f7-aa31-7ab99f8492ab", "lemma": "['small', 'overall', 'experience']", "sentence": "However something this small did not take away from the overall experience", "cpt": "0", "category": "atmosphere"}, {"id": 7, "date": "2018-07-16", "uid": "d303f25a-af0f-40ee-9ad9-5ff7d5d8a2ee", "lemma": "['call', 'expedia', 'explain', 'situation', 'disappointing', 'experience', 'wonderful', 'book', 'hilton', 'cura\u00e7ao']", "sentence": "So we called Expedia explained our situation and they made a very disappointing experience into a wonderful one by booking us into the Hilton Cura\u00e7ao", "cpt": "0", "category": "atmosphere"}, {"id": 8, "date": "2018-08-31", "uid": "d72b6d6a-1001-48dd-9fd4-22921a1d0bbd", "lemma": "['stay', 'lot', 'hilton', 'resorts', 'bad', 'experience', 'facility']", "sentence": "I have stayed at a lot of Hilton Resorts this is defiantly the worst experience I have ever had with the facilities", "cpt": "0", "category": "atmosphere"}, {"id": 9, "date": "2019-02-11", "uid": "3ec6eec1-9f97-4e5b-8583-13450f9a3f30", "lemma": "['bad', 'accommodation', 'experience']", "sentence": "This was by far the worse accommodations I have ever experienced", "cpt": "0", "category": "atmosphere"}, {"id": 10, "date": "2019-12-09", "uid": "ad617f6a-f8bf-4ace-9fec-438120626b55", "lemma": "['professional', 'want', 'honest', 'feedback', 'experience']", "sentence": "He was very professional and genuinely wanted to get our honest feedback on our experience there", "cpt": "1", "category": "atmosphere"}, {"id": 11, "date": "2019-12-26", "uid": "cf11957a-0ed2-4c9b-8e41-05e84cfc1b20", "lemma": "['wonderful', 'experience', 'stay']", "sentence": "Truly a wonderful experience and I would absolutely stay here again", "cpt": "1", "category": "atmosphere"}, {"id": 12, "date": "2020-01-07", "uid": "8815d2a5-3c01-4fe2-a538-f4add6b92f64", "lemma": "['bring', 'good', 'memory', 'stay']", "sentence": "We brought home the best memories from our stay", "cpt": "1", "category": "atmosphere"}, {"id": 13, "date": "2020-02-06", "uid": "219f83d5-976e-418d-8824-b6ee48d681ec", "lemma": "['feel', 'good', 'vibe']", "sentence": "when she is around you feel a really good vibe", "cpt": "1", "category": "atmosphere"}, {"id": 14, "date": "2020-02-10", "uid": "539637f5-d3dd-4e92-bdeb-75275e3cd9b0", "lemma": "['want', 'thank', 'fadilah', 'thank', 'kind', 'eager', 'help', 'love', 'vibe']", "sentence": "I want to especially thank Fadilah and ca n\u2019t thank her enough for all she did for us she was very kind and so eager to help just loved her vibe", "cpt": "1", "category": "atmosphere"}, {"id": 15, "date": "2020-02-15", "uid": "0f9a1141-29d3-4325-9c70-6da5825a0f76", "lemma": "['amazing', 'friendly', 'good', 'vibe']", "sentence": "She is amazing friendly and have a good vibe", "cpt": "1", "category": "atmosphere"}, {"id": 16, "date": "2020-02-17", "uid": "3e86a26e-1269-4c12-8d05-024297aba24d", "lemma": "['relax', 'vibe', 'awesome', 'staff']", "sentence": "Relaxing vibes and awesome staff", "cpt": "1", "category": "atmosphere"}, {"id": 17, "date": "2020-02-25", "uid": "29056728-a2a5-421e-9511-c33ae163cb4a", "lemma": "['chef', 'main', 'restaurant', 'ensure', 'good', 'menu', 'high', 'quality', 'dining', 'experience']", "sentence": "The chef of the main restaurant ensures a very good menu and high quality dining experience", "cpt": "1", "category": "atmosphere"}, {"id": 18, "date": "2020-02-28", "uid": "9efc5dcf-d5d2-4e6d-8795-b51d03d6abbc", "lemma": "['spice', 'restaurant', 'awesome', 'gourmet', 'experience']", "sentence": "C Spice restaurant is an awesome gourmet experience", "cpt": "1", "category": "atmosphere"}, {"id": 19, "date": "2020-03-06", "uid": "c859f635-0865-4ed0-a014-60a024bd18be", "lemma": "['get', 'know', 'young', 'man', 'name', 'frensel', 'leith', 'amazing', 'show', 'in', 'out', 'island', 'beach', 'miss', 'experience', 'friendly', 'pig', 'playa', 'marie']", "sentence": "Got to know a young man named Frensel Leito who really was amazing showing us the ins and outs of the island beaches not to miss and experiences like the friendly pigs of Playa Marie", "cpt": "1", "category": "atmosphere"}]