[{"id": 0, "date": "2015-03-31", "uid": "2c0d9ef1-f62a-4267-818c-e34a4ea7ff4e", "lemma": "['victor', 'work', 'pool', 'area', 'phenomenal']", "sentence": "Victor who works the pool area is phenomenal", "cpt": "0", "category": "pool"}, {"id": 1, "date": "2015-12-26", "uid": "4a6f2878-6863-494a-85e6-d4a451788020", "lemma": "['room', 'nice', 'fancy', 'place', 'new', 'good', 'value', 'pool', 'beach', 'great']", "sentence": "The rooms were nice nothing fancy and the place is not new but it is a very good value and the pool and beach are great", "cpt": "0", "category": "pool"}, {"id": 2, "date": "2016-05-02", "uid": "6ce97e50-3852-428c-9c26-607cf68f5840", "lemma": "['breakfast', 'buffett', 'spa', 'beautiful', 'beach', 'pool', 'service', 'walk', 'distance', 'marina', 'beauty', 'hotelthe', 'con']", "sentence": "breakfast Buffet the spa beautiful beach pool side service walking distance to the marina and the beauty of the hotelThe cons", "cpt": "0", "category": "pool"}, {"id": 3, "date": "2016-06-24", "uid": "68be4795-e425-4e8f-b27b-0ec4ce081693", "lemma": "['great', 'view', 'room', 'nice', 'pool']", "sentence": "Great views from the room and very nice pool", "cpt": "0", "category": "pool"}, {"id": 4, "date": "2016-12-30", "uid": "dc99525a-48ad-4c6a-be9b-b1da3861a066", "lemma": "['weather', 'great', 'pool', 'good', 'day', 'xmas', 'lot', 'bed', 'take', 'towel', 'morning']", "sentence": "The weather was great the pool really good although our last 2 days were over Xmas so lots of beds taken with towels early in the morning", "cpt": "0", "category": "pool"}, {"id": 5, "date": "2017-02-06", "uid": "a6aa081b-c240-42bc-a764-75263df209d2", "lemma": "['general', 'manager', 'david', 'gauna', 'able', 'realize', 'people', 'come', 'resort', 'beach', 'pool', 'find', 'hotel', 'guest']", "sentence": "The General Manager David Gauna was able to realize that people come to this resort to be at the beach pool and that \u2019s where you will find most of the hotel guests", "cpt": "0", "category": "pool"}, {"id": 6, "date": "2017-07-10", "uid": "9f26b9d5-9f95-4695-8cda-df3c82989e98", "lemma": "['waiter', 'wait', 'restaurant', 'people', 'pool', 'beach', 'enthusiasm', 'energy', 'good']", "sentence": "The waiters waits for the restaurants and the people at the pool and the beach with much enthusiam and energy that was the best part", "cpt": "0", "category": "pool"}, {"id": 7, "date": "2017-10-12", "uid": "3b84031b-fde9-4039-8725-cce3ce286acd", "lemma": "['warren', 'pool', 'set', 'activity', 'want', 'give', 'great', 'information', 'turtle', 'sanctuary', 'locate', 'site']", "sentence": "Warren at the pool set us up with any activity we wanted and gave us great information about he turtle sanctuary located on site", "cpt": "0", "category": "pool"}, {"id": 8, "date": "2018-01-22", "uid": "af9b9fdb-5e74-4e62-ad0d-641a52302485", "lemma": "['lunch', 'pool', 'easy', 'great', 'food']", "sentence": "Lunch by the pool is always easy and great food", "cpt": "0", "category": "pool"}, {"id": 9, "date": "2018-04-19", "uid": "c301c480-7864-4854-93e7-639a0ebe8fd1", "lemma": "['great', 'poolside', 'service', 'food', 'drink', 'edquardo']", "sentence": "We had great polside service of food and drinks by Edquardo", "cpt": "0", "category": "pool"}, {"id": 10, "date": "2019-06-21", "uid": "e6cdeb8e-a231-4dd0-a71c-3bd0fa32ecef", "lemma": "['resort', 'nice', 'find', 'book', 'pool', 'remodel', 'mean', 'shuttle', 'nearby', 'sister', 'hotel', 'use', 'pool']", "sentence": "the resort is quite nice however we found out after booking that their pool was being remodeled so that meant we had to take a shuttle to a nearby sister hotel to use their pool", "cpt": "1", "category": "pool"}, {"id": 11, "date": "2019-06-24", "uid": "2e3b9fd8-fcab-410c-9530-f4a56a395aa8", "lemma": "['sister', 'property', 'pool', 'door', 'shuttle', 'nice', 'music', 'dj', 'bunch', 'kid', 'pool', 'pack']", "sentence": "We used their sister property pool next door via shuttle and it was n\u2019t nice either no music DJ bunch of kids and the pool was always packed", "cpt": "1", "category": "pool"}, {"id": 12, "date": "2019-06-24", "uid": "2e3b9fd8-fcab-410c-9530-f4a56a395aa8", "lemma": "['pool', 'construction', 'summertime', 'big', 'downfall', 'vacation']", "sentence": "The pool being under construction in the summertime was the biggest downfall of this whole vacation", "cpt": "1", "category": "pool"}, {"id": 13, "date": "2019-08-02", "uid": "f5c60041-d090-42d9-9907-b1188108c665", "lemma": "['pool', 'amazing', 'fact', 'construction', 'happen', 'pool', 'leave', 'area', 'close']", "sentence": "The pool was amazing despite the fact that they had construction happening on one side of the pool that left that area closed off", "cpt": "1", "category": "pool"}, {"id": 14, "date": "2019-08-04", "uid": "1a81bd49-6d09-4041-9937-b3a2bf69ac8c", "lemma": "['raul', 'good', 'waiter', 'pool', 'area']", "sentence": "Raul is the best waiter by the pool area", "cpt": "1", "category": "pool"}, {"id": 15, "date": "2019-08-23", "uid": "8185cc58-6a52-41a8-8b2a-32a796ca05f6", "lemma": "['construction', 'pool', 'affect', 'use', 'pool']", "sentence": "There was construction on part of the pool but it did not affect our use of the pool", "cpt": "2", "category": "pool"}, {"id": 16, "date": "2019-08-28", "uid": "065b3d38-c411-4830-ac18-34499911ebd5", "lemma": "['wait', 'staff', 'pool', 'good', 'food', 'expensive']", "sentence": "The wait staff at the pool are good too The food were the worst even though they are ridiculously expensive", "cpt": "2", "category": "pool"}, {"id": 17, "date": "2019-09-12", "uid": "90714651-ce87-4db6-af85-9a9ccb47d141", "lemma": "['spa', 'restaurant', 'store', 'pool', 'concierge', 'service']", "sentence": "Spas restaurants stores pools concierge service and so much more", "cpt": "2", "category": "pool"}, {"id": 18, "date": "2019-10-02", "uid": "ec8b4663-e85d-456e-a957-739a1af5f9e7", "lemma": "['pool', 'nice', 'large', 'service', 'pool', 'slow']", "sentence": "While the pool was nice and large service by the pool was extremely slow", "cpt": "2", "category": "pool"}, {"id": 19, "date": "2019-11-19", "uid": "959dea87-480e-4a4e-98d1-91bb5a8783d9", "lemma": "['pool', 'service', 'food', 'close', 'restaurant', 'great', 'fast']", "sentence": "The pool side service was the same food as the two closest restaurants and it was great and fast", "cpt": "2", "category": "pool"}, {"id": 20, "date": "2019-11-19", "uid": "959dea87-480e-4a4e-98d1-91bb5a8783d9", "lemma": "['lot', 'entry', 'point', 'lounger', 'water', 'hammock', 'middle', 'pool']", "sentence": "there are lots of entry points they have loungers in the water hammocks in the middle of the pool", "cpt": "2", "category": "pool"}, {"id": 21, "date": "2020-01-22", "uid": "f3d4b49c-5953-4ba4-9e52-0af9cb9c5edd", "lemma": "['pool', 'area', 'remodel', 'nice']", "sentence": "The pool area has been remodeled and is even nicer than before", "cpt": "2", "category": "pool"}, {"id": 22, "date": "2020-01-29", "uid": "e7458e09-6f38-460e-a19c-87586856965f", "lemma": "['security', 'team', 'pull', 'room', 'access', 'time', 'show', 'time', 'access', 'time', 'pool', 'verify', 'waiter', 'friend']", "sentence": "The security team pulled up the room access times and showed the time that it was accessed which was during the time we were at the pool and this can be verified by our waiter and our friends we were with", "cpt": "2", "category": "pool"}, {"id": 23, "date": "2020-03-07", "uid": "a7c2c93d-6793-4b4c-b37c-9bd63b2d1e49", "lemma": "['fact', 'people', 'block', 'chair', 'pool', 'towel', 'house', 'opportunity', 'sit', 'want']", "sentence": "The fact that people Block The chairs around The pool with their towels for house and do n\u2019t give others The opportunity to sit where they want to", "cpt": "2", "category": "pool"}]