[{"id": 0, "date": "2015-01-22", "uid": "310201fa-0091-487d-ac2b-ffb52a9d7682", "lemma": "['cheap', 'hotel', 'pay']", "sentence": "Cheap Hotel you get what you pay for", "cpt": "0", "category": "price"}, {"id": 1, "date": "2015-02-16", "uid": "fb386011-962d-47bc-9c41-80975bedbfec", "lemma": "['good', 'price', 'near', 'convenient']", "sentence": "Good price and everything is near by very convinient", "cpt": "0", "category": "price"}, {"id": 2, "date": "2015-02-28", "uid": "eccf8a02-6340-4ec5-9783-de1aeb6684a7", "lemma": "['great', 'price', 'well', 'location']", "sentence": "Great price better location", "cpt": "0", "category": "price"}, {"id": 3, "date": "2015-03-25", "uid": "1ecc4c8e-2846-4f42-a7ff-431608b8f6d8", "lemma": "['good', 'hotel', 'avalon', 'price']", "sentence": "Good hotel on Avalon for the price", "cpt": "0", "category": "price"}, {"id": 4, "date": "2015-04-08", "uid": "215ad2d2-d213-4db1-9951-786df4791d59", "lemma": "['worth', 'good', 'hotel', 'hand', 'price']", "sentence": "Totally worth it best hotel there hands down for the price", "cpt": "0", "category": "price"}, {"id": 5, "date": "2015-06-09", "uid": "c6561188-6709-4f00-93e4-6354a25bd0b1", "lemma": "['price', 'room', 'reasonable', 'hotel']", "sentence": "Price of room was the most reasonable of all the hotels", "cpt": "0", "category": "price"}, {"id": 6, "date": "2015-06-16", "uid": "8b5a678a-0eaa-4ca7-ac0e-bad84b8feb36", "lemma": "['rate', 'reasonable', 'catalina']", "sentence": "Rates reasonable for Catalina", "cpt": "0", "category": "price"}, {"id": 7, "date": "2015-06-24", "uid": "419b399b-e48a-4a81-9cdd-89daf4efde1d", "lemma": "['great', 'location', 'great', 'price', 'decent', 'accomodation']", "sentence": "Great location great price decent acomodations", "cpt": "0", "category": "price"}, {"id": 8, "date": "2015-07-21", "uid": "9ff18548-0d2a-4c21-b38f-0fbe102bcf4f", "lemma": "['good', 'place', 'price']", "sentence": "Best place for the price", "cpt": "0", "category": "price"}, {"id": 9, "date": "2015-07-23", "uid": "ec968225-d3e9-464c-b970-06f4a28e2574", "lemma": "['staff', 'friendly', 'price', 'budget']", "sentence": "staff is friendly price is within my budget", "cpt": "0", "category": "price"}, {"id": 10, "date": "2015-08-05", "uid": "698ddb15-1133-4a66-bda1-e0feb5bdee79", "lemma": "['price', 'high', 'room']", "sentence": "Price was high for the rooms", "cpt": "1", "category": "price"}, {"id": 11, "date": "2015-08-11", "uid": "2beddc3b-4cc7-4208-92ee-24d18eec259c", "lemma": "['price', 'little', 'high', 'problem']", "sentence": "Price seemed a little high but that is a problem everywhere now", "cpt": "1", "category": "price"}, {"id": 12, "date": "2016-04-27", "uid": "9f94414c-0ac8-4a58-80df-6479f8da0354", "lemma": "['extra', 'item', 'expensive', 'buy', 'pastry', 'local', 'sons']", "sentence": "Any extra item was expensive better buy some pastries at the local Vons", "cpt": "1", "category": "price"}, {"id": 13, "date": "2016-07-27", "uid": "28a1c6e0-93fe-4983-87d0-b0629fe81e19", "lemma": "['will', 'stay', 'extend', 'check', 'check', 'willing', 'pay', 'extra']", "sentence": "I wo nt stay here no more because they can not extend the check in not even the check out no matter what even i am willing to pay extra", "cpt": "1", "category": "price"}, {"id": 14, "date": "2016-07-27", "uid": "ccfb91bc-89f7-4618-8a75-d55e89b5e436", "lemma": "['disappointed', 'pay', 'room', 'get']", "sentence": "I was disappointed that we paid 400 for the room we got", "cpt": "1", "category": "price"}, {"id": 15, "date": "2016-10-06", "uid": "5d272c6e-6d74-41c3-8968-6dbf66c51a44", "lemma": "['hotel', 'staff', 'st', 'rate']", "sentence": "Hotel Staff is 1st rate", "cpt": "1", "category": "price"}, {"id": 16, "date": "2017-07-03", "uid": "492f7bd2-26da-432d-aabc-c84c7af3329a", "lemma": "['like', 'hotel', 'believe', 'price']", "sentence": "I still liked this hotel I just could not believe the price", "cpt": "1", "category": "price"}, {"id": 17, "date": "2017-07-06", "uid": "1d561ca3-4d7d-4844-a8ff-ce306a147e12", "lemma": "['expensive', 'pretty', 'old', 'hotel']", "sentence": "A little expensive for this pretty old hotel", "cpt": "1", "category": "price"}, {"id": 18, "date": "2017-07-16", "uid": "906527eb-b356-4512-899b-8608862f5ec5", "lemma": "['room', 'rate', 'little', 'expensive', 'accommodation']", "sentence": "The room rate was a little expensive for the accommodations", "cpt": "1", "category": "price"}, {"id": 19, "date": "2017-10-06", "uid": "2027b7c6-a562-46c1-ae33-a0238e55d65a", "lemma": "['expensive', 'quality', 'receive', 'price', 'catalina', 'island']", "sentence": "it is very expensive for the quality you receive but moderately priced for Catalina Island", "cpt": "1", "category": "price"}]