[{"id": 0, "date": "2015-01-07", "uid": "c1d9c19b-1f37-43d9-bcca-2945f751ce73", "lemma": "['ask', 'bar', 'doubletree', 'martini', 'mixture', 'vodka', 'butterscotch', 'liquer', 'baileys']", "sentence": "Ask the bar to make you a Doubletree Martini which is a mixture of vodka butterscotch liquer and baileys", "cpt": "0", "category": "restaurant"}, {"id": 1, "date": "2015-07-06", "uid": "17ff50eb-cd8f-418e-bc7c-0225a6d3e8c0", "lemma": "['go', 'breakfast', 'ask', 'want', 'buffet', 'order', 'menu', 'say', 'buffet', 'fine']", "sentence": "Then i went down to breakfast and was asked if I wanted the buffet or to order off a menu and I said the buffet was fine", "cpt": "0", "category": "restaurant"}, {"id": 2, "date": "2015-11-10", "uid": "5a0c1050-ac06-44d1-9e1f-e8fc25615285", "lemma": "['terrible', 'bar', 'service', 'serve', 'center', 'bar', 'ignore', 'side']", "sentence": "Terrible bar service they only served the center of the bar and ignored the sides", "cpt": "0", "category": "restaurant"}, {"id": 3, "date": "2016-05-13", "uid": "a99e42b0-192b-4aee-ad44-fbe2d0c6b12b", "lemma": "['nice', 'bar', 'fridge', 'safe', 'room']", "sentence": "it will be nice to have a bar fridge and a safe in the room", "cpt": "0", "category": "restaurant"}, {"id": 4, "date": "2017-01-24", "uid": "1711da6a-d869-4c98-9cb4-6f1abcc8fdfe", "lemma": "['restaurant', 'undergo', 'facelift', 'displace', 'area']", "sentence": "The restaurant is also undergoing a facelift so was displaced in another area", "cpt": "0", "category": "restaurant"}, {"id": 5, "date": "2017-02-01", "uid": "cb0a948c-b762-4e81-8a9d-e35e45140e0a", "lemma": "['disappoint', 'find', 'entire', 'lobby', 'area', 'snack', 'area', 'fitness', 'room', 'unavailable', 'use', 'construction']", "sentence": "I was disappointed to find that the entire lobby area snack area and fitness room were unavailable for use due to construction", "cpt": "0", "category": "restaurant"}, {"id": 6, "date": "2017-06-01", "uid": "b670f91e-8d0d-4d68-9745-efe334563fa8", "lemma": "['restaurant', 'fast', 'food', 'chain', 'restaurant']", "sentence": "There are a few restaurants but I did not see very many fast food or chain restaurants", "cpt": "0", "category": "restaurant"}, {"id": 7, "date": "2017-07-09", "uid": "23c5bc48-dbcf-4dd4-9c61-f376c89820f2", "lemma": "['sit', 'dining', 'area']", "sentence": "You have to sit in the dining area", "cpt": "0", "category": "restaurant"}, {"id": 8, "date": "2017-09-09", "uid": "f7370a26-c2d7-4518-bde3-c112b86e3943", "lemma": "['cleanliness', 'suggestion', 'clean', 'shower', 'bar', 'soap', 'scum', 'evident']", "sentence": "Only cleanliness suggestion clean back from of shower bars soap scum evident", "cpt": "0", "category": "restaurant"}, {"id": 9, "date": "2017-10-12", "uid": "c1a93ddd-80f5-4d62-ab35-07ac8c3dccba", "lemma": "['nice', 'bar', 'pool', 'room', 'small', 'nice']", "sentence": "Had a nice bar and pools but the rooms were very small and not very nice", "cpt": "0", "category": "restaurant"}, {"id": 10, "date": "2018-01-08", "uid": "0d20cc2c-a2ea-45f7-b37b-b2e1c9cbdf78", "lemma": "['lot', 'drink', 'food', 'special', 'bar']", "sentence": "Lots of drink and food specials at the bar", "cpt": "1", "category": "restaurant"}, {"id": 11, "date": "2018-04-03", "uid": "fbf8ecef-2cc2-4b26-a357-8380b5d3c018", "lemma": "['go', 'fccla', 'conference', 'ask', 'ice', 'water', 'bar', 'get', 'staff', 'nice', 'ballroom', 'nice', 'atmosphere', 'elevator', 'slow']", "sentence": "Went here for an FCLA conference asked for ice water at bar and got it quickly staff was nice ballroom had a nice atmosphere elevator was slow", "cpt": "1", "category": "restaurant"}, {"id": 12, "date": "2018-07-11", "uid": "730ab824-cac2-4f1a-974a-3823e5ef2521", "lemma": "['sit', 'renovate', 'tavern', 'pool', 'enjoy', 'competitive', 'game', 'uno', 'have', 'dinner', 'swimsuit']", "sentence": "We sat out on the newly renovated tavern by the pool and enjoyed a competitive game of UNO while casually having dinner in our swimsuits", "cpt": "1", "category": "restaurant"}, {"id": 13, "date": "2018-12-07", "uid": "8b719831-5698-4310-bc24-984fa9a507e2", "lemma": "['renovated', 'lobby', 'bar', 'restaurant', 'look', 'fantastic']", "sentence": "Renovated lobby bar and restaurant look fantastic", "cpt": "1", "category": "restaurant"}, {"id": 14, "date": "2019-02-09", "uid": "379ae73d-8b47-4f0f-9490-2726b35c4679", "lemma": "['friendly', 'staff', 'restaurant', 'good', 'hotel', 'update', 'clean']", "sentence": "Very friendly staff restaurant was very good and the hotel was updated and very clean", "cpt": "1", "category": "restaurant"}, {"id": 15, "date": "2019-04-19", "uid": "0fc95b77-90fd-4287-a332-96179ff4dc2a", "lemma": "['breakfast', 'buffet', 'decent', 'lot', 'choose']", "sentence": "Breakfast buffet was pretty decent and had lots to choose from", "cpt": "1", "category": "restaurant"}, {"id": 16, "date": "2019-06-16", "uid": "4fe3add0-0136-4d6f-8bc3-3cb7daf5316c", "lemma": "['hotel', 'stay', 'complementary', 'breakfast']", "sentence": "Every hotel we \u2019ve stayed at have Complementary breakfast", "cpt": "1", "category": "restaurant"}, {"id": 17, "date": "2019-08-16", "uid": "fa2f2dee-2188-416c-9194-9d85bb73c04c", "lemma": "['service', 'great', 'breakfast', 'hotel', 'double', 'tree', 'standard', 'opinion']", "sentence": "Service is great and so was the breakfast but the hotel is not up to the double tree standard in my opinion", "cpt": "1", "category": "restaurant"}, {"id": 18, "date": "2019-11-01", "uid": "35548cb1-9fde-402c-a374-f5a372b157e5", "lemma": "['wine', 'small', 'ample', 'bar', 'delicious', 'breakfastwill', 'plan', 'stay']", "sentence": "The wine from the small but ample bar was delicious as was the breakfastWil definitely plan to stay here again", "cpt": "1", "category": "restaurant"}, {"id": 19, "date": "2019-11-17", "uid": "7de92e3e-67ae-45d7-a209-20c45d07b6d5", "lemma": "['arrive', 'evening', 'desk', 'restaurant', 'staff', 'accommodating']", "sentence": "Arrived later evening front desk and restaurant staff were very accommodating", "cpt": "1", "category": "restaurant"}]